jirate/__init__.py
jirate/args.py
jirate/board.py
jirate/cli.py
jirate/config.py
jirate/decor.py
jirate/jboard.py
jirate/jira_cli.py
jirate/jira_custom.py
jirate/jira_fields.py
jirate/jira_input.py
jirate/localstate.py
jirate/rqcache.py
jirate/template_vars.py
jirate/schemas/issue.yaml
jirate/schemas/subtask.yaml
jirate/schemas/template.yaml
jirate/tests/__init__.py
jirate/tests/test_args.py
jirate/tests/test_config.py
jirate/tests/test_decor.py
jirate/tests/test_fields.py
jirate/tests/test_input.py
jirate/tests/test_jira_cli.py
jirate/tests/test_jira_custom.py
jirate/tests/test_jirate.py
jirate/tests/test_render.py
jirate/tests/test_rqcache.py
jirate/tests/test_schemas.py
jirate/tests/test_template_vars.py
jirate/tests/templates/bad-template.yaml
jirate/tests/templates/good-template.yaml
jirate-0.8.21.data/data/LICENSE.txt
jirate-0.8.21.dist-info/METADATA
jirate-0.8.21.dist-info/WHEEL
jirate-0.8.21.dist-info/entry_points.txt
jirate-0.8.21.dist-info/licenses/LICENSE.txt
jirate-0.8.21.dist-info/RECORD
