Metadata-Version: 2.4
Name: jirate
Version: 0.8.21
Project-URL: Homepage, http://github.com/lhh/jirate
Author-email: Red Hat <lhh@redhat.com>
Maintainer-email: Lon Hohberger <lon@metamorphism.com>
License: Copyright (c) 2012, Fog Creek Software, Inc.
License-File: LICENSE.txt
Classifier: Development Status :: 4 - Beta
Classifier: Intended Audience :: Developers
Classifier: Natural Language :: English
Classifier: Operating System :: MacOS :: MacOS X
Classifier: Operating System :: Microsoft :: Windows
Classifier: Operating System :: POSIX
Classifier: Operating System :: POSIX :: BSD
Classifier: Operating System :: POSIX :: Linux
Classifier: Programming Language :: Python
Classifier: Topic :: Internet :: WWW/HTTP
Classifier: Topic :: Software Development
Classifier: Topic :: Software Development :: Libraries
Classifier: Topic :: Software Development :: Libraries :: Python Modules
Classifier: Topic :: Utilities
Requires-Python: >=3.9
Requires-Dist: editor>=1.2.1
Requires-Dist: jinja2>=3.0.0
Requires-Dist: jira>=3.8.0
Requires-Dist: jsonschema>=4.18.0a1
Requires-Dist: prettytable
Requires-Dist: python-dateutil
Requires-Dist: pyyaml
Requires-Dist: referencing
Requires-Dist: requests>=2.0.0
Requires-Dist: rich
Requires-Dist: toolchest
Requires-Dist: trollo>=0.2.4
